{
  "source": "http://www.geonames.org/AF/administrative-division-afghanistan.html",
  "country": "Afghanistan",
  "subdivisions": {
    "BAL": "Balkh province",
    "BAM": "Bamian province",
    "BDG": "Badghis province",
    "BDS": "Badakhshan province",
    "BGL": "Baghlan province",
    "DAY": "Dāykundī",
    "FRA": "Farah province",
    "FYB": "Faryab province",
    "GHA": "Ghazni province",
    "GHO": "Ghowr province",
    "HEL": "Helmand province",
    "HER": "Herat province",
    "JOW": "Jowzjan province",
    "KAB": "Kabul province",
    "KAN": "Kandahar province",
    "KAP": "Kapisa province",
    "KDZ": "Kondoz province",
    "KHO": "Khost province",
    "KNR": "Konar province",
    "LAG": "Laghman province",
    "LOG": "Lowgar province",
    "NAN": "Nangrahar province",
    "NIM": "Nimruz province",
    "NUR": "Nurestan province",
    "PAN": "Panjshir",
    "PAR": "Parwan province",
    "PIA": "Paktia province",
    "PKA": "Paktika province",
    "SAM": "Samangan province",
    "SAR": "Sar-e Pol province",
    "TAK": "Takhar province",
    "URU": "Uruzgān province",
    "WAR": "Wardak province",
    "ZAB": "Zabol province"
  }
}
